vrmlxpy/__init__.py
vrmlxpy/libboost_filesystem.so.1.74.0
vrmlxpy/libboost_iostreams.so.1.74.0
vrmlxpy/libboost_log.so.1.74.0
vrmlxpy/libboost_thread.so.1.74.0
vrmlxpy/libtogeom.so
vrmlxpy/libvrmlproc.so
vrmlxpy/togeom.dll
vrmlxpy/vrmlproc.dll
vrmlxpy/vrmlxpy.cp310-win_amd64.pyd
vrmlxpy/vrmlxpy.so
vrmlxpy-1.0.4.dist-info/licenses/LICENSE
vrmlxpy-1.0.4.dist-info/METADATA
vrmlxpy-1.0.4.dist-info/WHEEL
vrmlxpy-1.0.4.dist-info/top_level.txt
vrmlxpy-1.0.4.dist-info/RECORD
