Metadata-Version: 2.4
Name: vrmlxpy
Version: 1.0.4
Summary: Toolkit for VRML parsing and traversing. Includes a standalone VRML parser library and a conversion library for transforming VRML geometry into geometry format such as STL, with modular C++ backends and Python bindings.
Home-page: https://github.com/kerrambit/vrmlxpy
Author: Marek Eibel
License: GPL-3.0-or-later
Keywords: vrml,stl,3d,graphics,bindings
Classifier: Programming Language :: Python :: 3
Classifier: Programming Language :: C++
Classifier: Operating System :: Microsoft :: Windows
Classifier: Operating System :: POSIX :: Linux
Requires-Python: >=3.10
License-File: LICENSE
Dynamic: home-page
Dynamic: license-file
Dynamic: requires-python
